deidcm/__init__.py
deidcm/config.py
deidcm/deid_verification.py
deidcm/df2dicom_verification.py
deidcm/dicom2png.py
deidcm/dicom/__init__.py
deidcm/dicom/deid_mammogram.py
deidcm/dicom/df2dicom.py
deidcm/dicom/dicom2df.py
deidcm/dicom/recipe.json
deidcm/dicom/utils.py
deidcm/test_cases/__init__.py
deidcm/test_cases/cases.py
deidcm-0.0.3.dist-info/LICENSE
deidcm-0.0.3.dist-info/METADATA
deidcm-0.0.3.dist-info/WHEEL
deidcm-0.0.3.dist-info/top_level.txt
deidcm-0.0.3.dist-info/RECORD
