Metadata-Version: 2.1
Name: deidcm
Version: 0.0.3
Summary: Reusable toolset for deidentifiying images and metadata contained inside DICOM files
Home-page: https://github.com/Epiconcept-Paris/deidcm
Author: ['Francisco Orchard', 'William Madié']
Author-email: ['f.orchard@epiconcept.fr', 'w.madie@epiconcept.fr']
License: MIT License
Requires-Python: >=3.6
License-File: LICENSE
Requires-Dist: easyocr
Requires-Dist: opencv-python
Requires-Dist: opencv-python-headless
Requires-Dist: Numpy >=1.21.6
Requires-Dist: matplotlib
Requires-Dist: pandas
Requires-Dist: pillow
Requires-Dist: pydicom
Provides-Extra: mkdocs
Requires-Dist: mkdocs ; extra == 'mkdocs'
Requires-Dist: mkdocs-material ; extra == 'mkdocs'
Requires-Dist: mkdocs-material-extensions ; extra == 'mkdocs'
Requires-Dist: mkdocstrings-python ; extra == 'mkdocs'
Requires-Dist: pymdown-extensions ; extra == 'mkdocs'
Requires-Dist: mkdocs-pymdownx-material-extras ; extra == 'mkdocs'
Provides-Extra: quality-tools
Requires-Dist: pylint ; extra == 'quality-tools'
Requires-Dist: autopep8 ; extra == 'quality-tools'
Requires-Dist: pytest ; extra == 'quality-tools'
Requires-Dist: coverage ; extra == 'quality-tools'
Requires-Dist: pytest-cov ; extra == 'quality-tools'
